Metadata-Version: 1.0
Name: dada-cache
Version: 0.0.9
Summary: Re-usable caching objects for dada-lake
Home-page: http://globally.ltd
Author: gltd
Author-email: hey@gltd.email
License: UNKNOWN
Platform: UNKNOWN
